setup.py
NBLSpiderORM/Builder.py
NBLSpiderORM/Config.py
NBLSpiderORM/Connection.py
NBLSpiderORM/Connectionpool.py
NBLSpiderORM/DBModel.py
NBLSpiderORM/Expression.py
NBLSpiderORM/Logger.py
NBLSpiderORM/Response.py
NBLSpiderORM/__init__.py
NBLSpiderORM.egg-info/PKG-INFO
NBLSpiderORM.egg-info/SOURCES.txt
NBLSpiderORM.egg-info/dependency_links.txt
NBLSpiderORM.egg-info/entry_points.txt
NBLSpiderORM.egg-info/requires.txt
NBLSpiderORM.egg-info/top_level.txt