Metadata-Version: 1.0
Name: NBLSpiderORM
Version: 0.0.4
Summary: NBLSpiderORM
Home-page: https://www.nbltrust.com/#/cn/home
Author: nbltrust
Author-email: UNKNOWN
License: UNKNOWN
Platform: UNKNOWN
